LICENSE
MANIFEST.in
README.md
setup.py
moneta/__init__.py
moneta/archives.py
moneta/conf.py
moneta/context_processors.py
moneta/defaults.py
moneta/exceptions.py
moneta/iniconf.py
moneta/root_urls.py
moneta/urls.py
moneta/utils.py
moneta/views.py
moneta.egg-info/PKG-INFO
moneta.egg-info/SOURCES.txt
moneta.egg-info/dependency_links.txt
moneta.egg-info/entry_points.txt
moneta.egg-info/not-zip-safe
moneta.egg-info/requires.txt
moneta.egg-info/top_level.txt
moneta/__pycache__/__init__.cpython-36.pyc
moneta/__pycache__/archives.cpython-36.pyc
moneta/__pycache__/conf.cpython-36.pyc
moneta/__pycache__/context_processors.cpython-36.pyc
moneta/__pycache__/defaults.cpython-36.pyc
moneta/__pycache__/exceptions.cpython-36.pyc
moneta/__pycache__/iniconf.cpython-36.pyc
moneta/__pycache__/root_urls.cpython-36.pyc
moneta/__pycache__/urls.cpython-36.pyc
moneta/__pycache__/utils.cpython-36.pyc
moneta/__pycache__/views.cpython-36.pyc
moneta/locale/README
moneta/locale/fr_FR/LC_MESSAGES/django.mo
moneta/locale/fr_FR/LC_MESSAGES/django.po
moneta/management/__init__.py
moneta/management/__pycache__/__init__.cpython-36.pyc
moneta/management/commands/__init__.py
moneta/management/commands/add_element.py
moneta/migrations/0001_initial.py
moneta/migrations/__init__.py
moneta/migrations/__pycache__/0001_initial.cpython-36.pyc
moneta/migrations/__pycache__/__init__.cpython-36.pyc
moneta/repositories/__init__.py
moneta/repositories/aptitude.py
moneta/repositories/base.py
moneta/repositories/flat_files.py
moneta/repositories/jetbrains.py
moneta/repositories/maven3.py
moneta/repositories/models.py
moneta/repositories/pypi.py
moneta/repositories/rpm.py
moneta/repositories/ruby.py
moneta/repositories/vagrant.py
moneta/repositories/xmlrpc.py
moneta/repositories/yum.py
moneta/repositories/__pycache__/__init__.cpython-36.pyc
moneta/repositories/__pycache__/aptitude.cpython-36.pyc
moneta/repositories/__pycache__/base.cpython-36.pyc
moneta/repositories/__pycache__/flat_files.cpython-36.pyc
moneta/repositories/__pycache__/jetbrains.cpython-36.pyc
moneta/repositories/__pycache__/maven3.cpython-36.pyc
moneta/repositories/__pycache__/models.cpython-36.pyc
moneta/repositories/__pycache__/pypi.cpython-36.pyc
