Metadata-Version: 1.1
Name: moneta
Version: 1.8.11
Summary: Emulator for different kinds (Debian/Yum/Pypi/Maven/…) of package repositories on the same server.
Home-page: https://moneta.readthedocs.io/
Author: flanker
Author-email: flanker@19pouces.net
License: CeCILL-B
Platform: UNKNOWN
Classifier: Development Status :: 5 - Production/Stable
Classifier: Framework :: Django :: 1.11
Classifier: Framework :: Django :: 2.0
Classifier: Natural Language :: English
Classifier: Natural Language :: French
Classifier: Operating System :: MacOS :: MacOS X
Classifier: Operating System :: POSIX :: BSD
Classifier: Operating System :: POSIX :: Linux
Classifier: Operating System :: Unix
Classifier: License :: OSI Approved :: CEA CNRS Inria Logiciel Libre License, version 2.1 (CeCILL-2.1)
Classifier: Programming Language :: Python :: 3.5
Classifier: Programming Language :: Python :: 3.6
Classifier: Programming Language :: Python :: 3.7
Classifier: Programming Language :: Python :: 3 :: Only
